src/__init__.py
src/class_names.txt
src/main.py
src/ontology.json
src/csv/balanced_train_segments.csv
src/csv/eval_segments.csv
src/csv/unbalanced_train_segments.csv
audioset_downloader-0.1.1.dist-info/LICENSE
audioset_downloader-0.1.1.dist-info/METADATA
audioset_downloader-0.1.1.dist-info/WHEEL
audioset_downloader-0.1.1.dist-info/entry_points.txt
audioset_downloader-0.1.1.dist-info/top_level.txt
audioset_downloader-0.1.1.dist-info/RECORD
